findreplace/__init__.py
findreplace/__version__.py
findreplace/cli.py
findreplace/core.py
findreplace-2018.6.24.1.dist-info/METADATA
findreplace-2018.6.24.1.dist-info/RECORD
findreplace-2018.6.24.1.dist-info/WHEEL
findreplace-2018.6.24.1.dist-info/entry_points.txt
findreplace-2018.6.24.1.dist-info/top_level.txt
