Metadata-Version: 2.1
Name: findreplace
Version: 2018.6.24.1
Summary: Go through a directory recursively, find and replace specified values in file names and file data.
Home-page: https://github.com/djstein/findreplace
Author: Dylan Stein
Author-email: djstein@ncsu.edu
License: UNKNOWN
Platform: UNKNOWN
Classifier: Programming Language :: Python
Classifier: Programming Language :: Python :: 3.6
Classifier: Programming Language :: Python :: Implementation :: CPython
Classifier: Programming Language :: Python :: Implementation :: PyPy
Requires-Dist: click
Requires-Dist: requests
